pglift/__init__.py
pglift/_compat.py
pglift/abc.py
pglift/backup.py
pglift/conf.py
pglift/databases.py
pglift/deps.py
pglift/diff.py
pglift/exceptions.py
pglift/extensions.py
pglift/hba.py
pglift/hookspecs.py
pglift/instances.py
pglift/passfile.py
pglift/pm.py
pglift/privileges.py
pglift/profiles.py
pglift/publications.py
pglift/py.typed
pglift/replication_slots.py
pglift/roles.py
pglift/schemas.py
pglift/subscriptions.py
pglift/task.py
pglift/testutil.py
pglift/types.py
pglift/ui.py
pglift/util.py
pglift/annotations/__init__.py
pglift/annotations/ansible.py
pglift/annotations/cli.py
pglift/fixtures/__init__.py
pglift/fixtures/etcd.py
pglift/fixtures/functional.py
pglift/fixtures/types.py
pglift/fixtures/unit.py
pglift/logrotate/__init__.py
pglift/manager/__init__.py
pglift/manager/configuration.py
pglift/manager/hba.py
pglift/manager/instance.py
pglift/models/__init__.py
pglift/models/helpers.py
pglift/models/interface.py
pglift/models/system.py
pglift/models/testing.py
pglift/models/types.py
pglift/models/validators.py
pglift/patroni/__init__.py
pglift/patroni/dcs.py
pglift/patroni/impl.py
pglift/patroni/logrotate.conf
pglift/patroni/logrotate.conf.license
pglift/patroni/patroni.yaml
pglift/patroni/patroni.yaml.license
pglift/patroni/models/__init__.py
pglift/patroni/models/build.py
pglift/patroni/models/common.py
pglift/patroni/models/interface.py
pglift/patroni/models/system.py
pglift/pgbackrest/__init__.py
pglift/pgbackrest/base.py
pglift/pgbackrest/logrotate.conf
pglift/pgbackrest/logrotate.conf.license
pglift/pgbackrest/pgbackrest.conf
pglift/pgbackrest/pgbackrest.conf.license
pglift/pgbackrest/repo_host_ssh.py
pglift/pgbackrest/repo_host_tls.py
pglift/pgbackrest/repo_path.py
pglift/pgbackrest/server.conf
pglift/pgbackrest/server.conf.license
pglift/pgbackrest/models/__init__.py
pglift/pgbackrest/models/interface.py
pglift/pgbackrest/models/system.py
pglift/postgresql/__init__.py
pglift/postgresql/ctl.py
pglift/postgresql/logrotate.conf
pglift-2.6.1.dist-info/METADATA
pglift-2.6.1.dist-info/WHEEL
pglift-2.6.1.dist-info/RECORD
