Metadata-Version: 2.4
Name: pglift
Version: 2.6.1
Summary: Life-cycle management of production-ready PostgreSQL instances
Project-URL: Documentation, https://pglift.readthedocs.io/
Project-URL: Source, https://gitlab.com/dalibo/pglift/
Project-URL: Tracker, https://gitlab.com/dalibo/pglift/-/issues/
Author-email: Dalibo SCOP <contact@dalibo.com>
License: GPLv3
Keywords: administration,deployment,postgresql
Classifier: Development Status :: 5 - Production/Stable
Classifier: Intended Audience :: Developers
Classifier: Intended Audience :: System Administrators
Classifier: License :: OSI Approved :: GNU General Public License v3 (GPLv3)
Classifier: Programming Language :: Python :: 3
Classifier: Programming Language :: Python :: 3 :: Only
Classifier: Programming Language :: Python :: 3.10
Classifier: Programming Language :: Python :: 3.11
Classifier: Programming Language :: Python :: 3.12
Classifier: Programming Language :: Python :: 3.13
Classifier: Programming Language :: Python :: 3.14
Classifier: Topic :: Database
Classifier: Topic :: System :: Systems Administration
Classifier: Typing :: Typed
Requires-Python: <4,>=3.10
Requires-Dist: async-lru
Requires-Dist: attrs>=21.3.0
Requires-Dist: backports-datetime-fromisoformat; python_version < '3.11'
Requires-Dist: fsspec
Requires-Dist: httpx<1,>=0.28
Requires-Dist: humanize
Requires-Dist: pgtoolkit>=0.33.0
Requires-Dist: pluggy
Requires-Dist: psutil
Requires-Dist: psycopg>=3.1
Requires-Dist: pydantic-settings
Requires-Dist: pydantic>=2.10.2
Requires-Dist: python-dateutil
Requires-Dist: python-dotenv
Requires-Dist: pyyaml>=6.0.1
Requires-Dist: tenacity!=8.4.0,>=8.2.0
Requires-Dist: typing-extensions
Provides-Extra: cli
Requires-Dist: pglift-cli; extra == 'cli'
Provides-Extra: dev
Requires-Dist: ansible-core; extra == 'dev'
Requires-Dist: anyio>=4.9.0; extra == 'dev'
Requires-Dist: httpx<1,>=0.28; extra == 'dev'
Requires-Dist: mypy>=1.10.0; extra == 'dev'
Requires-Dist: patroni[etcd]>=2.1.5; extra == 'dev'
Requires-Dist: port-for; extra == 'dev'
Requires-Dist: pytest-cov; extra == 'dev'
Requires-Dist: pytest>=8; extra == 'dev'
Requires-Dist: tenacity!=8.2.0,!=8.4.0,>=8.0.0; extra == 'dev'
Requires-Dist: trustme; extra == 'dev'
Requires-Dist: types-psutil; extra == 'dev'
Requires-Dist: types-python-dateutil; extra == 'dev'
Requires-Dist: types-pyyaml>=6.0.12.10; extra == 'dev'
Provides-Extra: test
Requires-Dist: ansible-core; extra == 'test'
Requires-Dist: anyio>=4.9.0; extra == 'test'
Requires-Dist: httpx<1,>=0.28; extra == 'test'
Requires-Dist: patroni[etcd]>=2.1.5; extra == 'test'
Requires-Dist: port-for; extra == 'test'
Requires-Dist: pytest-cov; extra == 'test'
Requires-Dist: pytest>=8; extra == 'test'
Requires-Dist: tenacity!=8.2.0,!=8.4.0,>=8.0.0; extra == 'test'
Requires-Dist: trustme; extra == 'test'
Provides-Extra: typing
Requires-Dist: mypy>=1.10.0; extra == 'typing'
Requires-Dist: types-psutil; extra == 'typing'
Requires-Dist: types-python-dateutil; extra == 'typing'
Requires-Dist: types-pyyaml>=6.0.12.10; extra == 'typing'
